sophgoapi/__init__.py
sophgoapi/main.so
sophgoapi/object_detection/__init__.py
sophgoapi/object_detection/analysis/__init__.py
sophgoapi/object_detection/analysis/gather_detect.so
sophgoapi/object_detection/analysis/occlusion_detect.so
sophgoapi/object_detection/config/__init__.py
sophgoapi/object_detection/config/alarm_rules.yml
sophgoapi/object_detection/config/base.yml
sophgoapi/object_detection/models/__init__.py
sophgoapi/object_detection/models/builder.so
sophgoapi/object_detection/models/inference.so
sophgoapi/object_detection/models/liu.jpg
sophgoapi/object_detection/models/predictor.so
sophgoapi/object_detection/models/recognizer.so
sophgoapi/object_detection/post_processing/__init__.py
sophgoapi/object_detection/post_processing/postprocess.so
sophgoapi/object_detection/post_processing/recognition_mode/__init__.py
sophgoapi/object_detection/post_processing/recognition_mode/main.so
sophgoapi/object_detection/post_processing/recognition_mode/matcher.so
sophgoapi/object_detection/post_processing/recognition_mode/target.so
sophgoapi/object_detection/post_processing/recognition_mode/utils.so
sophgoapi/object_detection/pre_processing/__init__.py
sophgoapi/object_detection/pre_processing/deblur_select/__init__.py
sophgoapi/object_detection/pre_processing/deblur_select/evaluation.so
sophgoapi/object_detection/pre_processing/deblur_select/select_image.so
sophgoapi/object_detection/pre_processing/night_vision_detection/__init__.py
sophgoapi/object_detection/pre_processing/night_vision_detection/night_vision.so
sophgoapi/object_detection/pre_processing/similarity/__init__.py
sophgoapi/object_detection/pre_processing/similarity/main.so
sophgoapi/object_detection/pre_processing/similarity/utils.so
sophgoapi/object_detection/utils/__init__.py
sophgoapi/object_detection/utils/base_utils.so
sophgoapi/object_detection/utils/config.so
sophgoapi/object_detection/utils/logger.so
sophgoapi/object_detection/utils/parametar.so
sophgoapi/object_detection/utils/workspace.so
sophgoapi-1.0.5.dist-info/METADATA
sophgoapi-1.0.5.dist-info/WHEEL
sophgoapi-1.0.5.dist-info/top_level.txt
sophgoapi-1.0.5.dist-info/RECORD
