Metadata-Version: 2.1
Name: sophgoapi
Version: 1.0.5
Summary: sophgoapi
Home-page: UNKNOWN
Author: UNKNOWN
Author-email: UNKNOWN
License: Apache License 2.0
Platform: UNKNOWN
Requires-Dist: opencv-python (==4.10.0.84)
Requires-Dist: psutil
Requires-Dist: shapely (==2.0.6)
Requires-Dist: torch
Requires-Dist: torchvision
